{
  "start_hour": 11,
  "end_hour": 23,
  "evening_hour": 19,
  "unit_overrides": {
    "171611": "-30",
    "172254": "-30",
    "177451": "-10",
    "177492": "-30",
    "177494": "-30",
    "177498": "-10",
    "183003": "-15",
    "183008": "-15",
    "183016": "-15",
    "214892": "-20",
    "214894": "-20",
    "214952": "-20",
    "214991": "-20",
    "214995": "-20",
    "225320": "0",
    "241775": "0",
    "241890": "-20",
    "242199": "0",
    "242211": "0",
    "242428": "-20",
    "242505": "-20",
    "243598": "-20",
    "243848": "-20",
    "243973": "-20",
    "243974": "-20"
  }
}